renfepy/__init__.py
renfepy/console.py
renfepy/logger.py
renfepy/renfe.py
renfepy/models/train.py
renfepy/models/traintable.py
renfepy-2.0.0.dist-info/METADATA
renfepy-2.0.0.dist-info/WHEEL
renfepy-2.0.0.dist-info/entry_points.txt
renfepy-2.0.0.dist-info/top_level.txt
renfepy-2.0.0.dist-info/RECORD
