Metadata-Version: 2.1
Name: renfepy
Version: 2.0.0
Summary: Python library for crawl trains from renfe
Author-email: tekofx <tekofxx@gmail.com>
Project-URL: Homepage, https://github.com/tekofx/renfepy
Keywords: trains,crawl,selenium
Classifier: License :: OSI Approved :: MIT License
Classifier: Programming Language :: Python
Classifier: Programming Language :: Python :: 3
Requires-Python: >=3.9
Requires-Dist: selenium
Requires-Dist: rich
Requires-Dist: python-dateutil
Provides-Extra: dev
Requires-Dist: black ; extra == 'dev'
Requires-Dist: bumpver ; extra == 'dev'
Requires-Dist: isort ; extra == 'dev'
Requires-Dist: pip-tools ; extra == 'dev'
Requires-Dist: pytest ; extra == 'dev'
